docs/conf.py
__init__.py
__main__.py
cli.py
fntcommand_restclient-0.0.2.dist-info/METADATA
fntcommand_restclient-0.0.2.dist-info/WHEEL
fntcommand_restclient-0.0.2.dist-info/entry_points.txt
fntcommand_restclient-0.0.2.dist-info/licenses/LICENSE
fntcommand_restclient-0.0.2.dist-info/RECORD
