Metadata-Version: 2.1
Name: fntcommand-restclient
Version: 0.0.2
Summary: REST client for FNT Command (https://www.fntsoftware.com/en/products/fnt-command)
Requires-Python: >=3.6
